{"nodes": [{"id": "github_pr_template_legacy", "label": "pull_request_template.md \u2014 Legacy PR Template", "file_type": "document", "source_file": ".github/pull_request_template.md", "source_location": null, "source_url": null, "captured_at": null, "author": null, "contributor": null}], "edges": [{"source": "github_pr_template_legacy", "target": "agent_handoff_format", "relation": "includes", "confidence": "EXTRACTED", "confidence_score": 1.0, "source_file": ".github/pull_request_template.md", "source_location": "\u00a7Agent Handoff", "weight": 1.0}, {"source": "github_pr_template_legacy", "target": "check_pr_cleanliness_sh", "relation": "references", "confidence": "EXTRACTED", "confidence_score": 1.0, "source_file": ".github/pull_request_template.md", "source_location": "Checklist", "weight": 1.0}], "hyperedges": []}