{"nodes": [{"id": "home_user_projects_tomorrowland_review_12_md", "label": "12.md", "file_type": "document", "source_file": "/home/user/projects/Tomorrowland/review/12.md", "source_location": "L1"}, {"id": "review_12_review_pr_12", "label": "Review \u2014 PR #12", "file_type": "document", "source_file": "/home/user/projects/Tomorrowland/review/12.md", "source_location": "L1"}, {"id": "review_12_blockers_must_fix_before_merge", "label": "\u274c Blockers (must fix before merge)", "file_type": "document", "source_file": "/home/user/projects/Tomorrowland/review/12.md", "source_location": "L3"}, {"id": "review_12_warnings_should_fix", "label": "\u26a0\ufe0f Warnings (should fix)", "file_type": "document", "source_file": "/home/user/projects/Tomorrowland/review/12.md", "source_location": "L7"}, {"id": "review_12_suggestions_nice_to_have", "label": "\ud83d\udca1 Suggestions (nice-to-have)", "file_type": "document", "source_file": "/home/user/projects/Tomorrowland/review/12.md", "source_location": "L14"}, {"id": "review_12_coverage_report", "label": "\u2705 Coverage report", "file_type": "document", "source_file": "/home/user/projects/Tomorrowland/review/12.md", "source_location": "L20"}, {"id": "review_12_checklist", "label": "\ud83d\udccb Checklist", "file_type": "document", "source_file": "/home/user/projects/Tomorrowland/review/12.md", "source_location": "L28"}, {"id": "review_12_verdict", "label": "Verdict", "file_type": "document", "source_file": "/home/user/projects/Tomorrowland/review/12.md", "source_location": "L38"}], "edges": [{"source": "home_user_projects_tomorrowland_review_12_md", "target": "review_12_review_pr_12", "relation": "contains", "confidence": "EXTRACTED", "source_file": "/home/user/projects/Tomorrowland/review/12.md", "source_location": "L1", "weight": 1.0}, {"source": "review_12_review_pr_12", "target": "review_12_blockers_must_fix_before_merge", "relation": "contains", "confidence": "EXTRACTED", "source_file": "/home/user/projects/Tomorrowland/review/12.md", "source_location": "L3", "weight": 1.0}, {"source": "review_12_review_pr_12", "target": "review_12_warnings_should_fix", "relation": "contains", "confidence": "EXTRACTED", "source_file": "/home/user/projects/Tomorrowland/review/12.md", "source_location": "L7", "weight": 1.0}, {"source": "review_12_review_pr_12", "target": "review_12_suggestions_nice_to_have", "relation": "contains", "confidence": "EXTRACTED", "source_file": "/home/user/projects/Tomorrowland/review/12.md", "source_location": "L14", "weight": 1.0}, {"source": "review_12_review_pr_12", "target": "review_12_coverage_report", "relation": "contains", "confidence": "EXTRACTED", "source_file": "/home/user/projects/Tomorrowland/review/12.md", "source_location": "L20", "weight": 1.0}, {"source": "review_12_review_pr_12", "target": "review_12_checklist", "relation": "contains", "confidence": "EXTRACTED", "source_file": "/home/user/projects/Tomorrowland/review/12.md", "source_location": "L28", "weight": 1.0}, {"source": "review_12_review_pr_12", "target": "review_12_verdict", "relation": "contains", "confidence": "EXTRACTED", "source_file": "/home/user/projects/Tomorrowland/review/12.md", "source_location": "L38", "weight": 1.0}], "input_tokens": 0, "output_tokens": 0}